kd_tree/__init__.py
kd_tree/kdtree.py
weighted_kdtree/__init__.py
weighted_kdtree/kdtree.py
weighted_kdtree-0.1.3.dist-info/METADATA
weighted_kdtree-0.1.3.dist-info/WHEEL
weighted_kdtree-0.1.3.dist-info/top_level.txt
weighted_kdtree-0.1.3.dist-info/RECORD
