Metadata-Version: 2.1
Name: weighted-kdtree
Version: 0.1.3
Summary: UNKNOWN
Home-page: https://github.com/moni97/kdtreePython
Author: Monisha Siddananda Sampaths
Author-email: monisam97@gmail.com
License: UNKNOWN
Platform: UNKNOWN
